NiceEncryption/NiceEncryption.py
NiceEncryption/__init__.py
NiceEncryption-0.1.dist-info/METADATA
NiceEncryption-0.1.dist-info/WHEEL
NiceEncryption-0.1.dist-info/top_level.txt
NiceEncryption-0.1.dist-info/RECORD
