Metadata-Version: 2.1
Name: NiceEncryption
Version: 0.1
Summary: A Python package that encrypts and decrypts strings.
Home-page: https://github.com/SpiderDerp/NiceEncryption
Download-URL: https://github.com/SpiderDerp/NiceEncryption/archive/refs/tags/v0.1.tar.gz
Author: SpiderDerp
Author-email: sfsreeramrave@gmail.com
License: UNKNOWN
Keywords: python,encryption
Platform: UNKNOWN
